shamnet/__init__.py
shamnet/diff_stats.py
shamnet/generate_shamnet_traindata.py
shamnet/jaxnn_helpers.py
shamnet/latin_hypercube.py
shamnet/leja19_smf.py
shamnet/load_shamnet_traindata.py
shamnet/sample_shamnet_param_space.py
shamnet/sham_network.py
shamnet/shamnet_traindata.py
shamnet/shmf_bpl.py
shamnet/shmf_planck.py
shamnet/smf_scatter_convolution.py
shamnet/subhalo_mass_function.py
shamnet/utils.py
shamnet/data/shamnet_64_32_8_4.31.h5
shamnet/tests/__init__.py
shamnet/tests/test_jaxnn_helpers.py
shamnet/tests/test_latin_hypercube.py
shamnet/tests/test_leja19_smf.py
shamnet/tests/test_shamnet_training.py
shamnet/tests/test_shmf_bpl.py
shamnet/tests/test_shmf_planck.py
shamnet/tests/test_smf_scatter_convolution.py
shamnet/tests/test_subhalo_mass_function.py
shamnet/tests/test_trained_shamnet.py
shamnet/tests/test_utils.py
shamnet/tests/testing_data/SHAMnet11_tdata_SHAMnet11_tdata_SHAMnet11_testing_tdata.h5
shamnet/tests/testing_data/bpl_shmf_z0.h5
shamnet/tests/testing_data/bpl_shmf_z0p5.h5
shamnet/tests/testing_data/bpl_shmf_z1p0.h5
shamnet/tests/testing_data/bpl_shmf_z2p0.h5
shamnet-0.1.0.dist-info/LICENSE
shamnet-0.1.0.dist-info/METADATA
shamnet-0.1.0.dist-info/WHEEL
shamnet-0.1.0.dist-info/top_level.txt
shamnet-0.1.0.dist-info/RECORD
